README.md
setup.py
acfun/__init__.py
acfun/acfun.py
acfun/config.py
acfun/database.py
acfun/entity.py
acfun.egg-info/PKG-INFO
acfun.egg-info/SOURCES.txt
acfun.egg-info/dependency_links.txt
acfun.egg-info/entry_points.txt
acfun.egg-info/requires.txt
acfun.egg-info/top_level.txt